msgraph_stuff.py
msgraph_stuff-0.0.1.dist-info/LICENSE
msgraph_stuff-0.0.1.dist-info/METADATA
msgraph_stuff-0.0.1.dist-info/WHEEL
msgraph_stuff-0.0.1.dist-info/top_level.txt
msgraph_stuff-0.0.1.dist-info/RECORD
